CHANGELOG.txt
LICENSE.txt
MANIFEST.in
README.txt
setup.py
glib/__init__.py
glib.egg-info/PKG-INFO
glib.egg-info/SOURCES.txt
glib.egg-info/dependency_links.txt
glib.egg-info/top_level.txt